{
    "links": [
        {
            "authors": [
                [
                    {
                        "bitmap$0": false,
                        "ids": [
                            "1741124"
                        ],
                        "name": "L. Valiant",
                        "slug": "L.-Valiant",
                        "structuredName": {
                            "firstName": "Leslie",
                            "lastName": "Valiant",
                            "middleNames": [
                                "G."
                            ]
                        }
                    },
                    {
                        "fragments": [],
                        "text": "L. Valiant"
                    }
                ]
            ],
            "badges": [
                {
                    "id": "OPEN_ACCESS"
                }
            ],
            "citationContexts": [
                {
                    "context": {
                        "fragments": [],
                        "text": "definition of learnability (introduced in [ 32 ]) which, by incorporating all three of the aspects above, allows some nontrivial program classes to be learnable in a strong but plausible sense."
                    },
                    "intents": [
                        {
                            "id": "background"
                        }
                    ]
                },
                {
                    "context": {
                        "fragments": [],
                        "text": "Note that the algorithms of [ 32 ] and [33] for k-CNF (k-DNF) are NFP (NFN) in the stronger sense that the probability that C D-(i) = 0 (C D\u2019(i) = 0) is 1 rather than 1 - c. Here we use this weaker definition, since our negative results (Section 6) hold even for this weaker notion."
                    },
                    "intents": [
                        {
                            "id": "methodology"
                        }
                    ]
                },
                {
                    "context": {
                        "fragments": [],
                        "text": "PROOF. Every k-term-DNF formula FD is logically equivalent to some k-CNF formula Fc. whose size is polynomially related to the size of Fn. (If F. = Cf=, T,, then let F(. = fl (x,, , x,,, . . . , x,,), where the product is over all choices of x;, E T, , x,,ETz,..., x,, E Tk.) Use the algorithm of [ 32 ] to learn a k-CNF formula F that is-close enough to Fc (according to Df and D-) to satisfy the definition of learnability."
                    },
                    "intents": [
                        {
                            "id": "methodology"
                        }
                    ]
                },
                {
                    "context": {
                        "fragments": [],
                        "text": "In [ 32 ] and [33] it was shown that certain classes of concepts represented as Boolean expressions could be learned in a very strong sense: Whatever the probability distributions from which the examples and counterexamples were drawn, an expression from these classes distinguishing the examples from the"
                    },
                    "intents": [
                        {
                            "id": "background"
                        }
                    ]
                },
                {
                    "context": {
                        "fragments": [],
                        "text": "In [ 32 ] it was shown that k-CNF is NFP-learnable (and hence learnable) from positive examples only."
                    },
                    "intents": [
                        {
                            "id": "background"
                        }
                    ]
                },
                {
                    "context": {
                        "fragments": [],
                        "text": "4. ~-Formulas Are Not Learnable In [ 32 ], it was shown that the class of p-formulas (Boolean formulas in which each variable occurs at most once) are learnable, provided that the learning algorithm has available certain very powerful oracles."
                    },
                    "intents": [
                        {
                            "id": "background"
                        }
                    ]
                },
                {
                    "context": {
                        "fragments": [],
                        "text": "This is perhaps surprising in light of the results in [ 32 ] and [33] outlined in Section 2 that k-CNF and k-DNF are learnable."
                    },
                    "intents": [
                        {
                            "id": "result"
                        }
                    ]
                },
                {
                    "context": {
                        "fragments": [],
                        "text": "It is possible and often important to allow incompletely specified feature vectors also [ 32 ]."
                    },
                    "intents": [
                        {
                            "id": "background"
                        }
                    ]
                }
            ],
            "corpusId": 59712,
            "fieldsOfStudy": [
                "Computer Science"
            ],
            "id": "10ddb646feddc12337b5a755c72e153e37088c02",
            "isKey": false,
            "numCitedBy": 4191,
            "numCiting": 18,
            "paperAbstract": {
                "fragments": [],
                "text": "Humans appear to be able to learn new concepts without needing to be programmed explicitly in any conventional sense. In this paper we regard learning as the phenomenon of knowledge acquisition in the absence of explicit programming. We give a precise methodology for studying this phenomenon from a computational viewpoint. It consists of choosing an appropriate information gathering mechanism, the learning protocol, and exploring the class of concepts that can be learnt using it in a reasonable (polynomial) number of steps. We find that inherent algorithmic complexity appears to set serious limits to the range of concepts that can be so learnt. The methodology and results suggest concrete principles for designing realistic learning systems."
            },
            "slug": "A-theory-of-the-learnable-Valiant",
            "title": {
                "fragments": [],
                "text": "A theory of the learnable"
            },
            "tldr": {
                "abstractSimilarityScore": 46,
                "text": "This paper regards learning as the phenomenon of knowledge acquisition in the absence of explicit programming, and gives a precise methodology for studying this phenomenon from a computational viewpoint."
            },
            "venue": {
                "fragments": [],
                "text": "STOC '84"
            },
            "year": 1984
        },
        {
            "authors": [
                [
                    {
                        "bitmap$0": false,
                        "ids": [
                            "1689080"
                        ],
                        "name": "Rolf Wiehagen",
                        "slug": "Rolf-Wiehagen",
                        "structuredName": {
                            "firstName": "Rolf",
                            "lastName": "Wiehagen",
                            "middleNames": []
                        }
                    },
                    {
                        "fragments": [],
                        "text": "Rolf Wiehagen"
                    }
                ],
                [
                    {
                        "bitmap$0": false,
                        "ids": [
                            "1723667"
                        ],
                        "name": "R. Freivalds",
                        "slug": "R.-Freivalds",
                        "structuredName": {
                            "firstName": "Rusins",
                            "lastName": "Freivalds",
                            "middleNames": []
                        }
                    },
                    {
                        "fragments": [],
                        "text": "R. Freivalds"
                    }
                ],
                [
                    {
                        "bitmap$0": false,
                        "ids": [
                            "1744019"
                        ],
                        "name": "E. Kinber",
                        "slug": "E.-Kinber",
                        "structuredName": {
                            "firstName": "Efim",
                            "lastName": "Kinber",
                            "middleNames": [
                                "B."
                            ]
                        }
                    },
                    {
                        "fragments": [],
                        "text": "E. Kinber"
                    }
                ]
            ],
            "badges": [
                {
                    "id": "UNPAYWALL"
                }
            ],
            "citationContexts": [],
            "corpusId": 19607939,
            "fieldsOfStudy": [
                "Computer Science",
                "Mathematics"
            ],
            "id": "b447cf4f23531d1674180a4b8f5452dfad2a0250",
            "isKey": false,
            "numCitedBy": 56,
            "numCiting": 9,
            "paperAbstract": {
                "fragments": [],
                "text": ""
            },
            "slug": "On-the-Power-of-Probabilistic-Strategies-in-Wiehagen-Freivalds",
            "title": {
                "fragments": [],
                "text": "On the Power of Probabilistic Strategies in Inductive Inference"
            },
            "venue": {
                "fragments": [],
                "text": "Theor. Comput. Sci."
            },
            "year": 1984
        },
        {
            "authors": [
                [
                    {
                        "bitmap$0": false,
                        "ids": [
                            "2911738"
                        ],
                        "name": "D. Angluin",
                        "slug": "D.-Angluin",
                        "structuredName": {
                            "firstName": "Dana",
                            "lastName": "Angluin",
                            "middleNames": []
                        }
                    },
                    {
                        "fragments": [],
                        "text": "D. Angluin"
                    }
                ]
            ],
            "badges": [
                {
                    "id": "UNPAYWALL"
                },
                {
                    "id": "OPEN_ACCESS"
                }
            ],
            "citationContexts": [
                {
                    "context": {
                        "fragments": [
                            {
                                "end": 57,
                                "start": 51
                            }
                        ],
                        "text": "By (1) and (2) and the fact that (6,@ differs from (6, 1) in only the position n + i, it follows that $ = 1."
                    },
                    "intents": [
                        {
                            "id": "background"
                        }
                    ]
                }
            ],
            "corpusId": 11873053,
            "fieldsOfStudy": [
                "Mathematics"
            ],
            "id": "225331d1700a9544545cc7c54a63c1b485269ce7",
            "isKey": false,
            "numCitedBy": 2037,
            "numCiting": 11,
            "paperAbstract": {
                "fragments": [],
                "text": ""
            },
            "slug": "Learning-Regular-Sets-from-Queries-and-Angluin",
            "title": {
                "fragments": [],
                "text": "Learning Regular Sets from Queries and Counterexamples"
            },
            "venue": {
                "fragments": [],
                "text": "Inf. Comput."
            },
            "year": 1987
        },
        {
            "authors": [
                [
                    {
                        "bitmap$0": false,
                        "ids": [
                            "1733689"
                        ],
                        "name": "D. Haussler",
                        "slug": "D.-Haussler",
                        "structuredName": {
                            "firstName": "David",
                            "lastName": "Haussler",
                            "middleNames": []
                        }
                    },
                    {
                        "fragments": [],
                        "text": "D. Haussler"
                    }
                ]
            ],
            "badges": [
                {
                    "id": "OPEN_ACCESS"
                }
            ],
            "citationContexts": [],
            "corpusId": 8863452,
            "fieldsOfStudy": [
                "Computer Science"
            ],
            "id": "80feac7b0c5f1a0880cc8b0a980eb0583d68b711",
            "isKey": false,
            "numCitedBy": 29,
            "numCiting": 20,
            "paperAbstract": {
                "fragments": [],
                "text": "We show that the notion of bias in inductive concept learning can be quantified in a way that directly relates to learning performance, and that this quantitative theory of bias can provide guidance in the design of effective learning algorithms. We apply this idea by measuring some common language biases, including restriction to conjunctive concepts and conjunctive concepts with internal disjunction, and, guided by these measurements, develop learning algorithms or these classes of concepts that have provably good convergence properties."
            },
            "slug": "Quantifying-the-Inductive-Bias-in-Concept-Learning-Haussler",
            "title": {
                "fragments": [],
                "text": "Quantifying the Inductive Bias in Concept Learning (Extended Abstract)"
            },
            "tldr": {
                "abstractSimilarityScore": 98,
                "text": "It is shown that the notion of bias in inductive concept learning can be quantified in a way that directly relates to learning performance, and that this quantitative theory of bias can provide guidance in the design of effective learning algorithms."
            },
            "venue": {
                "fragments": [],
                "text": "AAAI"
            },
            "year": 1986
        },
        {
            "authors": [
                [
                    {
                        "bitmap$0": false,
                        "ids": [
                            "40642563"
                        ],
                        "name": "L. Blum",
                        "slug": "L.-Blum",
                        "structuredName": {
                            "firstName": "Lenore",
                            "lastName": "Blum",
                            "middleNames": []
                        }
                    },
                    {
                        "fragments": [],
                        "text": "L. Blum"
                    }
                ],
                [
                    {
                        "bitmap$0": false,
                        "ids": [
                            "143624243"
                        ],
                        "name": "M. Blum",
                        "slug": "M.-Blum",
                        "structuredName": {
                            "firstName": "Manuel",
                            "lastName": "Blum",
                            "middleNames": []
                        }
                    },
                    {
                        "fragments": [],
                        "text": "M. Blum"
                    }
                ]
            ],
            "badges": [
                {
                    "id": "UNPAYWALL"
                },
                {
                    "id": "OPEN_ACCESS"
                }
            ],
            "citationContexts": [],
            "corpusId": 38396727,
            "fieldsOfStudy": [
                "Computer Science"
            ],
            "id": "b26deee6b97eb231250290721d2baaa257f9270a",
            "isKey": false,
            "numCitedBy": 622,
            "numCiting": 20,
            "paperAbstract": {
                "fragments": [],
                "text": ""
            },
            "slug": "Toward-a-Mathematical-Theory-of-Inductive-Inference-Blum-Blum",
            "title": {
                "fragments": [],
                "text": "Toward a Mathematical Theory of Inductive Inference"
            },
            "venue": {
                "fragments": [],
                "text": "Inf. Control."
            },
            "year": 1975
        },
        {
            "authors": [
                [
                    {
                        "bitmap$0": false,
                        "ids": [
                            "145634459"
                        ],
                        "name": "M. Garey",
                        "slug": "M.-Garey",
                        "structuredName": {
                            "firstName": "M.",
                            "lastName": "Garey",
                            "middleNames": [
                                "R."
                            ]
                        }
                    },
                    {
                        "fragments": [],
                        "text": "M. Garey"
                    }
                ],
                [
                    {
                        "bitmap$0": false,
                        "ids": [
                            "2150444582"
                        ],
                        "name": "David S. Johnson",
                        "slug": "David-S.-Johnson",
                        "structuredName": {
                            "firstName": "David",
                            "lastName": "Johnson",
                            "middleNames": [
                                "S."
                            ]
                        }
                    },
                    {
                        "fragments": [],
                        "text": "David S. Johnson"
                    }
                ]
            ],
            "badges": [
                {
                    "id": "OPEN_ACCESS"
                }
            ],
            "citationContexts": [],
            "corpusId": 2211006,
            "fieldsOfStudy": [
                "Computer Science"
            ],
            "id": "bdede1e17c947540b50e6e2db9e8467ddc6e7336",
            "isKey": false,
            "numCitedBy": 47656,
            "numCiting": 25,
            "paperAbstract": {
                "fragments": [],
                "text": "Horn formulae play a prominent role in artificial intelligence and logic programming. In this paper we investigate the problem of optimal compression of propositional Horn production rule knowledge bases. The standard approach to this problem, consisting in the removal of redundant rules from a knowledge base, leads to an \"irredundant\" but not necessarily optimal knowledge base. We prove here that the number of rules in any irredundant Horn knowledge base involving n propositional variables is at most n 0 1 times the minimum possible number of rules. In order to formalize the optimal compression problem, we define a Boolean function of a knowledge base as being the function whose set of true points is the set of models of the knowledge base. In this way the optimal compression of production rule knowledge bases becomes a problem of Boolean function minimization. In this paper we prove that the minimization of Horn functions (i.e. Boolean functions associated to Horn knowledge bases) is..."
            },
            "slug": "Computers-and-Intractability:-A-Guide-to-the-Theory-Garey-Johnson",
            "title": {
                "fragments": [],
                "text": "Computers and Intractability: A Guide to the Theory of NP-Completeness"
            },
            "tldr": {
                "abstractSimilarityScore": 100,
                "text": "This is the second edition of a quarterly column the purpose of which is to provide a continuing update to the list of problems (NP-complete and harder) presented by M. R. Garey and myself in the authors' book \u2018\u2018Computers and Intractability: A Guide to the Theory of NP-Completeness\u2019\u2019."
            },
            "venue": {
                "fragments": [],
                "text": ""
            },
            "year": 1978
        },
        {
            "authors": [
                [
                    {
                        "bitmap$0": false,
                        "ids": [
                            "152471016"
                        ],
                        "name": "Carl H. Smith",
                        "slug": "Carl-H.-Smith",
                        "structuredName": {
                            "firstName": "Carl H.",
                            "lastName": "Smith",
                            "middleNames": []
                        }
                    },
                    {
                        "fragments": [],
                        "text": "Carl H. Smith"
                    }
                ],
                [
                    {
                        "bitmap$0": false,
                        "ids": [
                            "6303082"
                        ],
                        "name": "Mahendran Velauthapillai",
                        "slug": "Mahendran-Velauthapillai",
                        "structuredName": {
                            "firstName": "Mahendran",
                            "lastName": "Velauthapillai",
                            "middleNames": []
                        }
                    },
                    {
                        "fragments": [],
                        "text": "Mahendran Velauthapillai"
                    }
                ]
            ],
            "badges": [
                {
                    "id": "UNPAYWALL"
                }
            ],
            "citationContexts": [],
            "corpusId": 205093652,
            "fieldsOfStudy": [
                "Computer Science"
            ],
            "id": "c619ac7bf56978b97dcb26ca9ab4e3d8b6edee18",
            "isKey": false,
            "numCitedBy": 11,
            "numCiting": 19,
            "paperAbstract": {
                "fragments": [],
                "text": ""
            },
            "slug": "On-the-Inference-of-Approximate-Programs-Smith-Velauthapillai",
            "title": {
                "fragments": [],
                "text": "On the Inference of Approximate Programs"
            },
            "venue": {
                "fragments": [],
                "text": "Theor. Comput. Sci."
            },
            "year": 1990
        },
        {
            "authors": [
                [
                    {
                        "bitmap$0": false,
                        "ids": [
                            "2911738"
                        ],
                        "name": "D. Angluin",
                        "slug": "D.-Angluin",
                        "structuredName": {
                            "firstName": "Dana",
                            "lastName": "Angluin",
                            "middleNames": []
                        }
                    },
                    {
                        "fragments": [],
                        "text": "D. Angluin"
                    }
                ]
            ],
            "badges": [
                {
                    "id": "UNPAYWALL"
                }
            ],
            "citationContexts": [],
            "corpusId": 282116,
            "fieldsOfStudy": [
                "Mathematics"
            ],
            "id": "0cb74c670f4cb29afe63ff25df19d1ed7afe4429",
            "isKey": false,
            "numCitedBy": 800,
            "numCiting": 12,
            "paperAbstract": {
                "fragments": [],
                "text": ""
            },
            "slug": "Inductive-Inference-of-Formal-Languages-from-Data-Angluin",
            "title": {
                "fragments": [],
                "text": "Inductive Inference of Formal Languages from Positive Data"
            },
            "venue": {
                "fragments": [],
                "text": "Inf. Control."
            },
            "year": 1980
        },
        {
            "authors": [
                [
                    {
                        "bitmap$0": false,
                        "ids": [
                            "144299726"
                        ],
                        "name": "Thomas G. Dietterich",
                        "slug": "Thomas-G.-Dietterich",
                        "structuredName": {
                            "firstName": "Thomas",
                            "lastName": "Dietterich",
                            "middleNames": [
                                "G."
                            ]
                        }
                    },
                    {
                        "fragments": [],
                        "text": "Thomas G. Dietterich"
                    }
                ],
                [
                    {
                        "bitmap$0": false,
                        "ids": [
                            "2421006"
                        ],
                        "name": "R. Michalski",
                        "slug": "R.-Michalski",
                        "structuredName": {
                            "firstName": "Ryszard",
                            "lastName": "Michalski",
                            "middleNames": [
                                "S."
                            ]
                        }
                    },
                    {
                        "fragments": [],
                        "text": "R. Michalski"
                    }
                ]
            ],
            "badges": [
                {
                    "id": "OPEN_ACCESS"
                }
            ],
            "citationContexts": [],
            "corpusId": 62605382,
            "fieldsOfStudy": [
                "Education"
            ],
            "id": "76ec5daa8207d63150ce950118c1b222dd3b9c33",
            "isKey": false,
            "numCitedBy": 333,
            "numCiting": 31,
            "paperAbstract": {
                "fragments": [],
                "text": "Research in the area of learning structural descriptions from examples is reviewed, giving primary attention to methods of learning characteristic descriptions of single concepts. In particular, we examine methods for finding the maximally-specific conjunctive generalizations (MSC-generalizations) that cover all of the training examples of a given concept. Various important aspects of structural learning in general are examined, and several criteria for evaluating structural learning methods are presented. Briefly, these criteria include (i) adequacy of the representation language, (ii) generalization rules employed, (iii) computational efficiency, and (iv) flexibility and extensibility. Selected learning methods developed by Buchanan, et al., Hayes-Roth, Vere, Winston, and the authors are analyzed according to these criteria. Finally, some goals are suggested for future research."
            },
            "slug": "A-Comparative-Review-of-Selected-Methods-for-from-Dietterich-Michalski",
            "title": {
                "fragments": [],
                "text": "A Comparative Review of Selected Methods for Learning from Examples"
            },
            "tldr": {
                "abstractSimilarityScore": 41,
                "text": "Methods for finding the maximally-specific conjunctive generalizations (MSC-generalizations) that cover all of the training examples of a given concept are examined."
            },
            "venue": {
                "fragments": [],
                "text": ""
            },
            "year": 1983
        },
        {
            "authors": [
                [
                    {
                        "bitmap$0": false,
                        "ids": [
                            "118163360"
                        ],
                        "name": "J. Case",
                        "slug": "J.-Case",
                        "structuredName": {
                            "firstName": "John",
                            "lastName": "Case",
                            "middleNames": []
                        }
                    },
                    {
                        "fragments": [],
                        "text": "J. Case"
                    }
                ],
                [
                    {
                        "bitmap$0": false,
                        "ids": [
                            "152471016"
                        ],
                        "name": "Carl H. Smith",
                        "slug": "Carl-H.-Smith",
                        "structuredName": {
                            "firstName": "Carl H.",
                            "lastName": "Smith",
                            "middleNames": []
                        }
                    },
                    {
                        "fragments": [],
                        "text": "Carl H. Smith"
                    }
                ]
            ],
            "badges": [
                {
                    "id": "UNPAYWALL"
                },
                {
                    "id": "OPEN_ACCESS"
                }
            ],
            "citationContexts": [],
            "corpusId": 10701762,
            "fieldsOfStudy": [
                "Philosophy"
            ],
            "id": "706e9e8e7622d1c4d8571eeaab6f3d3099a00d12",
            "isKey": false,
            "numCitedBy": 388,
            "numCiting": 27,
            "paperAbstract": {
                "fragments": [],
                "text": ""
            },
            "slug": "Comparison-of-Identification-Criteria-for-Machine-Case-Smith",
            "title": {
                "fragments": [],
                "text": "Comparison of Identification Criteria for Machine Inductive Inference"
            },
            "venue": {
                "fragments": [],
                "text": "Theor. Comput. Sci."
            },
            "year": 1983
        },
        {
            "authors": [
                [
                    {
                        "bitmap$0": false,
                        "ids": [
                            "144342820"
                        ],
                        "name": "E. M. Gold",
                        "slug": "E.-M.-Gold",
                        "structuredName": {
                            "firstName": "E.",
                            "lastName": "Gold",
                            "middleNames": [
                                "Mark"
                            ]
                        }
                    },
                    {
                        "fragments": [],
                        "text": "E. M. Gold"
                    }
                ]
            ],
            "badges": [
                {
                    "id": "UNPAYWALL"
                },
                {
                    "id": "OPEN_ACCESS"
                }
            ],
            "citationContexts": [
                {
                    "context": {
                        "fragments": [],
                        "text": "It is shown that this model allows the learning of regular sets in polynomial time, whereas results from [l] and [ 20 ] showed that this was not possible from examples only unless P = NP."
                    },
                    "intents": [
                        {
                            "id": "result"
                        }
                    ]
                }
            ],
            "corpusId": 8943792,
            "fieldsOfStudy": [
                "Computer Science",
                "Mathematics"
            ],
            "id": "9dfa951bec812bd7b8c905c587bca50b7883a10f",
            "isKey": false,
            "numCitedBy": 802,
            "numCiting": 9,
            "paperAbstract": {
                "fragments": [],
                "text": ""
            },
            "slug": "Complexity-of-Automaton-Identification-from-Given-Gold",
            "title": {
                "fragments": [],
                "text": "Complexity of Automaton Identification from Given Data"
            },
            "venue": {
                "fragments": [],
                "text": "Inf. Control."
            },
            "year": 1978
        },
        {
            "authors": [
                [
                    {
                        "bitmap$0": false,
                        "ids": [
                            "47494927"
                        ],
                        "name": "L. Pitt",
                        "slug": "L.-Pitt",
                        "structuredName": {
                            "firstName": "Leonard",
                            "lastName": "Pitt",
                            "middleNames": []
                        }
                    },
                    {
                        "fragments": [],
                        "text": "L. Pitt"
                    }
                ]
            ],
            "badges": [
                {
                    "id": "OPEN_ACCESS"
                }
            ],
            "citationContexts": [],
            "corpusId": 27482797,
            "fieldsOfStudy": [
                "Mathematics"
            ],
            "id": "fd13795e1084331febabd694c635c168cb6e862e",
            "isKey": false,
            "numCitedBy": 61,
            "numCiting": 12,
            "paperAbstract": {
                "fragments": [],
                "text": "Inductive Inference Machines (IlMs) attempt to identify functions given only input-output pairs of the functions. Probabilistic IlMs are defined, as is the probability that a probabilistic IlM identifies a function with respect to two common identification criteria: EX and BC. Let ID denote either of these criteria. Then ID/sub prob/(p) is the family of sets of functions U for which there is a probabilistic IlM identifying every f /spl epsi/ U with probability /spl ges/ p. It is shown that for all positive integers n, ID/sub prob/(1/n) is properly contained in ID/sub prob/(1/(n+1)), and that this discrete hierarchy is the \"finest\" possible. This hierarchy is related to others in the literature."
            },
            "slug": "A-Characterization-of-Probabilistic-Inference-Pitt",
            "title": {
                "fragments": [],
                "text": "A Characterization of Probabilistic Inference"
            },
            "tldr": {
                "abstractSimilarityScore": 40,
                "text": "It is shown that for all positive integers n, ID/sub prob/(1/n) is properly contained in ID/ sub prob/( 1/(n+1)), and that this discrete hierarchy is the \"finest\" possible."
            },
            "venue": {
                "fragments": [],
                "text": "FOCS"
            },
            "year": 1984
        },
        {
            "authors": [
                [
                    {
                        "bitmap$0": false,
                        "ids": [
                            "1714765"
                        ],
                        "name": "V. Chv\u00e1tal",
                        "slug": "V.-Chv\u00e1tal",
                        "structuredName": {
                            "firstName": "Vasek",
                            "lastName": "Chv\u00e1tal",
                            "middleNames": []
                        }
                    },
                    {
                        "fragments": [],
                        "text": "V. Chv\u00e1tal"
                    }
                ]
            ],
            "badges": [],
            "citationContexts": [],
            "corpusId": 43555235,
            "fieldsOfStudy": [
                "Mathematics"
            ],
            "id": "b4e0ca86d00efc6c548939e3ed614bf64dd9d0ab",
            "isKey": false,
            "numCitedBy": 2505,
            "numCiting": 5,
            "paperAbstract": {
                "fragments": [],
                "text": "Let A be a binary matrix of size m \u00d7 n, let cT be a positive row vector of length n and let e be the column vector, all of whose m components are ones. The set-covering problem is to minimize cTx subject to Ax \u2265 e and x binary. We compare the value of the objective function at a feasible solution found by a simple greedy heuristic to the true optimum. It turns out that the ratio between the two grows at most logarithmically in the largest column sum of A. When all the components of cT are the same, our result reduces to a theorem established previously by Johnson and Lovasz."
            },
            "slug": "A-Greedy-Heuristic-for-the-Set-Covering-Problem-Chv\u00e1tal",
            "title": {
                "fragments": [],
                "text": "A Greedy Heuristic for the Set-Covering Problem"
            },
            "tldr": {
                "abstractSimilarityScore": 43,
                "text": "It turns out that the ratio between the two grows at most logarithmically in the largest column sum of A when all the components of cT are the same, which reduces to a theorem established previously by Johnson and Lovasz."
            },
            "venue": {
                "fragments": [],
                "text": "Math. Oper. Res."
            },
            "year": 1979
        },
        {
            "authors": [
                [
                    {
                        "bitmap$0": false,
                        "ids": [
                            "2911738"
                        ],
                        "name": "D. Angluin",
                        "slug": "D.-Angluin",
                        "structuredName": {
                            "firstName": "Dana",
                            "lastName": "Angluin",
                            "middleNames": []
                        }
                    },
                    {
                        "fragments": [],
                        "text": "D. Angluin"
                    }
                ]
            ],
            "badges": [
                {
                    "id": "UNPAYWALL"
                },
                {
                    "id": "OPEN_ACCESS"
                }
            ],
            "citationContexts": [],
            "corpusId": 205885265,
            "fieldsOfStudy": [
                "Mathematics",
                "Computer Science"
            ],
            "id": "d2cc9aecd8a9cc4d1cceac2380c7da9d116a8218",
            "isKey": false,
            "numCitedBy": 272,
            "numCiting": 15,
            "paperAbstract": {
                "fragments": [],
                "text": ""
            },
            "slug": "On-the-Complexity-of-Minimum-Inference-of-Regular-Angluin",
            "title": {
                "fragments": [],
                "text": "On the Complexity of Minimum Inference of Regular Sets"
            },
            "venue": {
                "fragments": [],
                "text": "Inf. Control."
            },
            "year": 1978
        },
        {
            "authors": [
                [
                    {
                        "bitmap$0": false,
                        "ids": [
                            "2911738"
                        ],
                        "name": "D. Angluin",
                        "slug": "D.-Angluin",
                        "structuredName": {
                            "firstName": "Dana",
                            "lastName": "Angluin",
                            "middleNames": []
                        }
                    },
                    {
                        "fragments": [],
                        "text": "D. Angluin"
                    }
                ],
                [
                    {
                        "bitmap$0": false,
                        "ids": [
                            "152471016"
                        ],
                        "name": "Carl H. Smith",
                        "slug": "Carl-H.-Smith",
                        "structuredName": {
                            "firstName": "Carl H.",
                            "lastName": "Smith",
                            "middleNames": []
                        }
                    },
                    {
                        "fragments": [],
                        "text": "Carl H. Smith"
                    }
                ]
            ],
            "badges": [
                {
                    "id": "OPEN_ACCESS"
                }
            ],
            "citationContexts": [],
            "corpusId": 3209224,
            "fieldsOfStudy": [
                "Computer Science"
            ],
            "id": "f6524a6b8e6091c0a11d665180a5ad94bbf1d3b4",
            "isKey": false,
            "numCitedBy": 900,
            "numCiting": 190,
            "paperAbstract": {
                "fragments": [],
                "text": "There has been a great deal of theoretical and experimental work in computer science on inductive inference systems, that is, systems that try to infer general rules from examples. However, a complete and applicable theory of such systems is still a distant goal. This survey highlights and explains the main ideas that have been developed in the study of inductive inference, with special emphasis on the relations between the general theory and the specific algorithms and implementations. 154 references."
            },
            "slug": "Inductive-Inference:-Theory-and-Methods-Angluin-Smith",
            "title": {
                "fragments": [],
                "text": "Inductive Inference: Theory and Methods"
            },
            "tldr": {
                "abstractSimilarityScore": 46,
                "text": "This survey highlights and explains the main ideas that have been developed in the study of inductive inference, with special emphasis on the relations between the general theory and the specific algorithms and implementations."
            },
            "venue": {
                "fragments": [],
                "text": "CSUR"
            },
            "year": 1983
        },
        {
            "authors": [
                [
                    {
                        "bitmap$0": false,
                        "ids": [
                            "2647026"
                        ],
                        "name": "A. Blumer",
                        "slug": "A.-Blumer",
                        "structuredName": {
                            "firstName": "Anselm",
                            "lastName": "Blumer",
                            "middleNames": []
                        }
                    },
                    {
                        "fragments": [],
                        "text": "A. Blumer"
                    }
                ],
                [
                    {
                        "bitmap$0": false,
                        "ids": [
                            "1683946"
                        ],
                        "name": "A. Ehrenfeucht",
                        "slug": "A.-Ehrenfeucht",
                        "structuredName": {
                            "firstName": "Andrzej",
                            "lastName": "Ehrenfeucht",
                            "middleNames": []
                        }
                    },
                    {
                        "fragments": [],
                        "text": "A. Ehrenfeucht"
                    }
                ],
                [
                    {
                        "bitmap$0": false,
                        "ids": [
                            "1733689"
                        ],
                        "name": "D. Haussler",
                        "slug": "D.-Haussler",
                        "structuredName": {
                            "firstName": "David",
                            "lastName": "Haussler",
                            "middleNames": []
                        }
                    },
                    {
                        "fragments": [],
                        "text": "D. Haussler"
                    }
                ],
                [
                    {
                        "bitmap$0": false,
                        "ids": [
                            "1794034"
                        ],
                        "name": "Manfred K. Warmuth",
                        "slug": "Manfred-K.-Warmuth",
                        "structuredName": {
                            "firstName": "Manfred",
                            "lastName": "Warmuth",
                            "middleNames": [
                                "K."
                            ]
                        }
                    },
                    {
                        "fragments": [],
                        "text": "Manfred K. Warmuth"
                    }
                ]
            ],
            "badges": [
                {
                    "id": "OPEN_ACCESS"
                }
            ],
            "citationContexts": [
                {
                    "context": {
                        "fragments": [],
                        "text": "The reader should consult [9] for further relationships between approximations for NP-hard optimization problems and learnability."
                    },
                    "intents": [
                        {
                            "id": "background"
                        }
                    ]
                }
            ],
            "corpusId": 5225434,
            "fieldsOfStudy": [
                "Computer Science"
            ],
            "id": "29b6251c84def0cbd35397c71fada0d22cd9409c",
            "isKey": false,
            "numCitedBy": 200,
            "numCiting": 34,
            "paperAbstract": {
                "fragments": [],
                "text": "We extend Valiant's learnability model to learning classes of concepts defined by regions in Euclidean space E\". Our methods lead to a unified treatment of some of Valiant's results, along with previous results of Pearl and Devroye and Wagner on distribution-free convergence of certain pattern recognition algorithms. We show that the essential condition for distribution-free learnability is finiteness of the Vapnik-Chervonenkis dimension, a simple combinatorial parameter of the class of concepts to be learned. Using this parameter, we analyze the complexity and closure properties of learnable classes. Authors A. Blumer and D. Haussler gratefully acknowledge the support of NSF grant IST-8317918, author A. Ehrenfeucht the support of NSF grant MCS-8305245, and author M. Warmuth the support of the Faculty Research Committee of the University of California at Santa Cruz. Part of this work was done while A. Blumer was visiting the University of California at Santa Cruz and M. Warmuth the Univer-"
            },
            "slug": "Classifying-learnable-geometric-concepts-with-the-Blumer-Ehrenfeucht",
            "title": {
                "fragments": [],
                "text": "Classifying learnable geometric concepts with the Vapnik-Chervonenkis dimension"
            },
            "tldr": {
                "abstractSimilarityScore": 41,
                "text": "It is shown that the essential condition for distribution-free learnability is finiteness of the Vapnik-Chervonenkis dimension, a simple combinatorial parameter of the class of concepts to be learned."
            },
            "venue": {
                "fragments": [],
                "text": "STOC '86"
            },
            "year": 1986
        },
        {
            "authors": [
                [
                    {
                        "bitmap$0": false,
                        "ids": [
                            "2555785"
                        ],
                        "name": "J. Royer",
                        "slug": "J.-Royer",
                        "structuredName": {
                            "firstName": "James",
                            "lastName": "Royer",
                            "middleNames": [
                                "S."
                            ]
                        }
                    },
                    {
                        "fragments": [],
                        "text": "J. Royer"
                    }
                ]
            ],
            "badges": [
                {
                    "id": "UNPAYWALL"
                }
            ],
            "citationContexts": [],
            "corpusId": 33692515,
            "fieldsOfStudy": [
                "Mathematics"
            ],
            "id": "585313e216218254c5480cf58004456f7b117791",
            "isKey": false,
            "numCitedBy": 30,
            "numCiting": 17,
            "paperAbstract": {
                "fragments": [],
                "text": ""
            },
            "slug": "Inductive-Inference-of-Approximations-Royer",
            "title": {
                "fragments": [],
                "text": "Inductive Inference of Approximations"
            },
            "venue": {
                "fragments": [],
                "text": "Inf. Control."
            },
            "year": 1986
        },
        {
            "authors": [
                [
                    {
                        "bitmap$0": false,
                        "ids": [
                            "2739396"
                        ],
                        "name": "Robert P. Daley",
                        "slug": "Robert-P.-Daley",
                        "structuredName": {
                            "firstName": "Robert",
                            "lastName": "Daley",
                            "middleNames": [
                                "P."
                            ]
                        }
                    },
                    {
                        "fragments": [],
                        "text": "Robert P. Daley"
                    }
                ]
            ],
            "badges": [
                {
                    "id": "UNPAYWALL"
                },
                {
                    "id": "OPEN_ACCESS"
                }
            ],
            "citationContexts": [],
            "corpusId": 24559380,
            "fieldsOfStudy": [
                "Mathematics"
            ],
            "id": "a46d2b3f0ae08ed19b58859f790f8f8f3b078b0d",
            "isKey": false,
            "numCitedBy": 35,
            "numCiting": 3,
            "paperAbstract": {
                "fragments": [],
                "text": ""
            },
            "slug": "On-the-Error-Correcting-Power-of-Pluralism-in-Daley",
            "title": {
                "fragments": [],
                "text": "On the Error Correcting Power of Pluralism in BC-Type Inductive Inference"
            },
            "venue": {
                "fragments": [],
                "text": "Theor. Comput. Sci."
            },
            "year": 1983
        },
        {
            "authors": [
                [
                    {
                        "bitmap$0": false,
                        "ids": [
                            "1713946"
                        ],
                        "name": "Y. Kodratoff",
                        "slug": "Y.-Kodratoff",
                        "structuredName": {
                            "firstName": "Yves",
                            "lastName": "Kodratoff",
                            "middleNames": []
                        }
                    },
                    {
                        "fragments": [],
                        "text": "Y. Kodratoff"
                    }
                ],
                [
                    {
                        "bitmap$0": false,
                        "ids": [
                            "2421006"
                        ],
                        "name": "R. Michalski",
                        "slug": "R.-Michalski",
                        "structuredName": {
                            "firstName": "Ryszard",
                            "lastName": "Michalski",
                            "middleNames": [
                                "S."
                            ]
                        }
                    },
                    {
                        "fragments": [],
                        "text": "R. Michalski"
                    }
                ]
            ],
            "badges": [],
            "citationContexts": [],
            "corpusId": 60974791,
            "fieldsOfStudy": [
                "Computer Science"
            ],
            "id": "f4971ff0f6ae626e78131bafa012eadfe8e238e2",
            "isKey": false,
            "numCitedBy": 306,
            "numCiting": 0,
            "paperAbstract": {
                "fragments": [],
                "text": "This book reflects the expansion of machine learning research through presentation of recent advances in the field. The book provides an account of current research directions. Major topics covered include the following: learning concepts and rules from examples; cognitive aspects of learning; learning by analogy; learning by observation and discovery; and an exploration of general aspects of learning."
            },
            "slug": "Machine-learning:-an-artificial-intelligence-volume-Kodratoff-Michalski",
            "title": {
                "fragments": [],
                "text": "Machine learning: an artificial intelligence approach volume III"
            },
            "tldr": {
                "abstractSimilarityScore": 92,
                "text": "This book reflects the expansion of machine learning research through presentation of recent advances in the field through an account of current research directions."
            },
            "venue": {
                "fragments": [],
                "text": ""
            },
            "year": 1990
        },
        {
            "authors": [
                [
                    {
                        "bitmap$0": false,
                        "ids": [
                            "145896360"
                        ],
                        "name": "John Gill",
                        "slug": "John-Gill",
                        "structuredName": {
                            "firstName": "John",
                            "lastName": "Gill",
                            "middleNames": []
                        }
                    },
                    {
                        "fragments": [],
                        "text": "John Gill"
                    }
                ]
            ],
            "badges": [
                {
                    "id": "UNPAYWALL"
                }
            ],
            "citationContexts": [],
            "corpusId": 15320656,
            "fieldsOfStudy": [
                "Computer Science"
            ],
            "id": "2842d53d0f2389618f8ad1c47d2ffef2c344d22f",
            "isKey": false,
            "numCitedBy": 486,
            "numCiting": 8,
            "paperAbstract": {
                "fragments": [],
                "text": "Probabilistic Turing machines are Turing machines with the ability to flip coins in order to make random decisions. We allow probabilistic Turing machines small but nonzero error probability in computing number-theoretic functions. An example is given of a function computable more quickly by probabilistic Turing machines than by deterministic Turing machines. It is shown how probabilistic linear-bounded automata can simulate nondeterministic linear-bounded automata."
            },
            "slug": "Computational-complexity-of-probabilistic-Turing-Gill",
            "title": {
                "fragments": [],
                "text": "Computational complexity of probabilistic Turing machines"
            },
            "tldr": {
                "abstractSimilarityScore": 49,
                "text": "It is shown how probabilisticlinear-bounded automata can simulate nondeterministic linear-bounding automata and an example is given of a function computable more quickly by Probabilistic Turing machines than by deterministic Turing machines."
            },
            "venue": {
                "fragments": [],
                "text": "STOC '74"
            },
            "year": 1974
        },
        {
            "authors": [
                [
                    {
                        "bitmap$0": false,
                        "ids": [
                            "145634459"
                        ],
                        "name": "M. Garey",
                        "slug": "M.-Garey",
                        "structuredName": {
                            "firstName": "M.",
                            "lastName": "Garey",
                            "middleNames": [
                                "R."
                            ]
                        }
                    },
                    {
                        "fragments": [],
                        "text": "M. Garey"
                    }
                ],
                [
                    {
                        "bitmap$0": false,
                        "ids": [
                            "2150444582"
                        ],
                        "name": "David S. Johnson",
                        "slug": "David-S.-Johnson",
                        "structuredName": {
                            "firstName": "David",
                            "lastName": "Johnson",
                            "middleNames": [
                                "S."
                            ]
                        }
                    },
                    {
                        "fragments": [],
                        "text": "David S. Johnson"
                    }
                ]
            ],
            "badges": [],
            "citationContexts": [],
            "corpusId": 10916858,
            "fieldsOfStudy": [
                "Mathematics",
                "Computer Science"
            ],
            "id": "6878ac143239e2dea07169d6f77b11f9f8f8789d",
            "isKey": false,
            "numCitedBy": 292,
            "numCiting": 26,
            "paperAbstract": {
                "fragments": [],
                "text": "Graph coloring problems, in which one would like to color the vertices of a given graph with a small number of colors so that no two adjacent vertices receive the same color, arise in many applications, including various scheduling and partitioning problems. In this paper the complexity and performance of algorithms which construct such colorings are investigated. For a graph G, let &khgr;(G) denote the minimum possible number of colors required to color G and, for any graph coloring algorithm A, let A(G) denote the number of colors used by A when applied to G. Since the graph coloring problem is known to be \u201cNP-complete,\u201d it is considered unlikely that any efficient algorithm can guarantee A(G) = &khgr;(G) for all input graphs. In this paper it is proved that even coming close to khgr;(G) with a fast algorithm is hard. Specifically, it is shown that if for some constant r < 2 and constant d there exists a polynomial-time algorithm A which guarantees A(G) \u2264 r\u00b7&khgr;(G) + d, then there also exists a polynomial-time algorithm A which guarantees A(G) = &khgr;(G)."
            },
            "slug": "The-Complexity-of-Near-Optimal-Graph-Coloring-Garey-Johnson",
            "title": {
                "fragments": [],
                "text": "The Complexity of Near-Optimal Graph Coloring"
            },
            "tldr": {
                "abstractSimilarityScore": 41,
                "text": "It is proved that even coming close to khgr;(G) with a fast algorithm is hard, and it is shown that if for some constant r < 2 and constant d there exists a polynomial-time algorithm A which guarantees A(G)."
            },
            "venue": {
                "fragments": [],
                "text": "J. ACM"
            },
            "year": 1976
        },
        {
            "authors": [
                [
                    {
                        "bitmap$0": false,
                        "ids": [
                            "2911738"
                        ],
                        "name": "D. Angluin",
                        "slug": "D.-Angluin",
                        "structuredName": {
                            "firstName": "Dana",
                            "lastName": "Angluin",
                            "middleNames": []
                        }
                    },
                    {
                        "fragments": [],
                        "text": "D. Angluin"
                    }
                ]
            ],
            "badges": [],
            "citationContexts": [],
            "corpusId": 18300595,
            "fieldsOfStudy": [
                "Computer Science"
            ],
            "id": "01fa2c3cc94a8d9de9b30a5488e67a5007e4856e",
            "isKey": false,
            "numCitedBy": 524,
            "numCiting": 64,
            "paperAbstract": {
                "fragments": [],
                "text": "A famdy of efficient algorithms for referring certain subclasses of the regular languages from fmtte posttwe samples is presented These subclasses are the k-reversible languages, for k = 0, 1, 2, . . . . For each k there is an algorithm for finding the smallest k-reversible language containing any fimte posluve sample. It ts shown how to use this algorithm to do correct identification m the ILmlt of the kreversible languages from posmve data A reversible language is one that Is k-reverstble for some k __ 0. An efficient algonthrn is presented for mfernng reversible languages from posmve and negative examples, and it is shown that it leads to correct identification m the hmlt of the class of reversible languages. Numerous examples are gtven to dlustrate the algorithms and their behawor"
            },
            "slug": "Inference-of-Reversible-Languages-Angluin",
            "title": {
                "fragments": [],
                "text": "Inference of Reversible Languages"
            },
            "tldr": {
                "abstractSimilarityScore": 52,
                "text": "An efficient algonthrn is presented for mfernng reversible languages from posmve and negative examples, and it is shown that it leads to correct identification m the hmlt of the class of reversible languages."
            },
            "venue": {
                "fragments": [],
                "text": "JACM"
            },
            "year": 1982
        },
        {
            "authors": [
                [
                    {
                        "bitmap$0": false,
                        "ids": [
                            "2911738"
                        ],
                        "name": "D. Angluin",
                        "slug": "D.-Angluin",
                        "structuredName": {
                            "firstName": "Dana",
                            "lastName": "Angluin",
                            "middleNames": []
                        }
                    },
                    {
                        "fragments": [],
                        "text": "D. Angluin"
                    }
                ]
            ],
            "badges": [
                {
                    "id": "UNPAYWALL"
                }
            ],
            "citationContexts": [],
            "corpusId": 26319590,
            "fieldsOfStudy": [
                "Computer Science",
                "Mathematics"
            ],
            "id": "96023b401177948fc7bc011f2e18f8f3a33f2ef7",
            "isKey": false,
            "numCitedBy": 568,
            "numCiting": 9,
            "paperAbstract": {
                "fragments": [],
                "text": ""
            },
            "slug": "Finding-Patterns-Common-to-a-Set-of-Strings-Angluin",
            "title": {
                "fragments": [],
                "text": "Finding Patterns Common to a Set of Strings"
            },
            "venue": {
                "fragments": [],
                "text": "J. Comput. Syst. Sci."
            },
            "year": 1980
        },
        {
            "authors": [
                [
                    {
                        "bitmap$0": false,
                        "ids": [
                            "1707322"
                        ],
                        "name": "Oded Goldreich",
                        "slug": "Oded-Goldreich",
                        "structuredName": {
                            "firstName": "Oded",
                            "lastName": "Goldreich",
                            "middleNames": []
                        }
                    },
                    {
                        "fragments": [],
                        "text": "Oded Goldreich"
                    }
                ],
                [
                    {
                        "bitmap$0": false,
                        "ids": [
                            "1706681"
                        ],
                        "name": "S. Goldwasser",
                        "slug": "S.-Goldwasser",
                        "structuredName": {
                            "firstName": "Shafi",
                            "lastName": "Goldwasser",
                            "middleNames": []
                        }
                    },
                    {
                        "fragments": [],
                        "text": "S. Goldwasser"
                    }
                ],
                [
                    {
                        "bitmap$0": false,
                        "ids": [
                            "1689467"
                        ],
                        "name": "S. Micali",
                        "slug": "S.-Micali",
                        "structuredName": {
                            "firstName": "Silvio",
                            "lastName": "Micali",
                            "middleNames": []
                        }
                    },
                    {
                        "fragments": [],
                        "text": "S. Micali"
                    }
                ]
            ],
            "badges": [
                {
                    "id": "UNPAYWALL"
                },
                {
                    "id": "OPEN_ACCESS"
                }
            ],
            "citationContexts": [],
            "corpusId": 17064126,
            "fieldsOfStudy": [
                "Computer Science",
                "Mathematics"
            ],
            "id": "990842135e0c3adf1cea5dcaaffcaa38ec2c7b47",
            "isKey": false,
            "numCitedBy": 1943,
            "numCiting": 68,
            "paperAbstract": {
                "fragments": [],
                "text": "A constructive theory of randomness for functions, based on computational complexity, is developed, and a pseudorandom function generator is presented. This generator is a deterministic polynomial-time algorithm that transforms pairs (<italic>g</italic>, <italic>r</italic>), where <italic>g</italic> is <italic>any</italic> one-way function and <italic>r</italic> is a random <italic>k</italic>-bit string, to polynomial-time computable functions \u0192<italic><subscrpt>r</subscrpt></italic>: {1, \u2026 , 2<italic><supscrpt>k</supscrpt></italic>} \u2192 {1, \u2026 , 2<italic><supscrpt>k</supscrpt></italic>}. These \u0192<italic><subscrpt>r</subscrpt></italic>'s cannot be distinguished from <italic>random</italic> functions by any probabilistic polynomial-time algorithm that asks and receives the value of a function at arguments of its choice. The result has applications in cryptography, random constructions, and complexity theory."
            },
            "slug": "How-to-construct-random-functions-Goldreich-Goldwasser",
            "title": {
                "fragments": [],
                "text": "How to construct random functions"
            },
            "tldr": {
                "abstractSimilarityScore": 78,
                "text": "A constructive theory of randomness for functions, based on computational complexity, is developed, and a pseudorandom function generator is presented that has applications in cryptography, random constructions, and complexity theory."
            },
            "venue": {
                "fragments": [],
                "text": "JACM"
            },
            "year": 1986
        },
        {
            "authors": [
                [
                    {
                        "bitmap$0": false,
                        "ids": [
                            "1718867"
                        ],
                        "name": "A. Wigderson",
                        "slug": "A.-Wigderson",
                        "structuredName": {
                            "firstName": "Avi",
                            "lastName": "Wigderson",
                            "middleNames": []
                        }
                    },
                    {
                        "fragments": [],
                        "text": "A. Wigderson"
                    }
                ]
            ],
            "badges": [
                {
                    "id": "OPEN_ACCESS"
                }
            ],
            "citationContexts": [
                {
                    "context": {
                        "fragments": [],
                        "text": "Even for 3-colorable graphs, the best approximation algorithm known only guarantees that the coloring found uses at most 3& colors, where n is the number of vertices in the graph [ 35 ]."
                    },
                    "intents": []
                }
            ],
            "corpusId": 15905532,
            "fieldsOfStudy": [
                "Mathematics"
            ],
            "id": "f659cd2b4a7ae3bc44b42846dd2e3dbd337754a9",
            "isKey": false,
            "numCitedBy": 22,
            "numCiting": 16,
            "paperAbstract": {
                "fragments": [],
                "text": "Let A be a graph coloring algorithm. Denote by <italic>-&-Agrave; (G)</italic> the ratio between the maximum number of colors A will use to color the graph <italic>G,</italic> and the chromatic number of <italic>G,</italic><subscrpt>x</subscrpt><italic>(G)</italic>. For most existing <bold>polynomial</bold> coloring algorithms, <italic>-&-Agrave;(G)</italic> can be as bad as O<italic>(n),</italic> where <italic>n</italic> is the number of vertices in <italic>G</italic>. The best currently known algorithm guarantees <italic>-&-Agrave; (G)-&-equil;O(n/</italic>log<italic>n</italic>). In this paper we present a simple and efficient coloring algorithm which guarantees <italic>-&-Agrave;(G)-&-le;x(G)n</italic> (equation), a considerable improvem-&-edot;nt over the current bounds."
            },
            "slug": "A-new-approximate-graph-coloring-algorithm-Wigderson",
            "title": {
                "fragments": [],
                "text": "A new approximate graph coloring algorithm"
            },
            "tldr": {
                "abstractSimilarityScore": 47,
                "text": "A simple and efficient coloring algorithm which guarantees-&-Agrave; (G)-&-le;x(G)n</italic> (equation), a considerable improve over the current bounds is presented."
            },
            "venue": {
                "fragments": [],
                "text": "STOC '82"
            },
            "year": 1982
        },
        {
            "authors": [
                [
                    {
                        "bitmap$0": false,
                        "ids": [
                            "145634459"
                        ],
                        "name": "M. Garey",
                        "slug": "M.-Garey",
                        "structuredName": {
                            "firstName": "M.",
                            "lastName": "Garey",
                            "middleNames": [
                                "R."
                            ]
                        }
                    },
                    {
                        "fragments": [],
                        "text": "M. Garey"
                    }
                ]
            ],
            "badges": [],
            "citationContexts": [],
            "corpusId": 232754604,
            "fieldsOfStudy": [
                "Computer Science"
            ],
            "id": "08421c787d9a9e2d9f5ba4bda1bfc9866fa4b04f",
            "isKey": false,
            "numCitedBy": 4057,
            "numCiting": 0,
            "paperAbstract": {
                "fragments": [],
                "text": ""
            },
            "slug": "Johnson:-computers-and-intractability:-a-guide-to-Garey",
            "title": {
                "fragments": [],
                "text": "Johnson: computers and intractability: a guide to the theory of np- completeness (freeman"
            },
            "venue": {
                "fragments": [],
                "text": ""
            },
            "year": 1979
        },
        {
            "authors": [
                [
                    {
                        "bitmap$0": false,
                        "ids": [
                            "1789075"
                        ],
                        "name": "J. Horning",
                        "slug": "J.-Horning",
                        "structuredName": {
                            "firstName": "James",
                            "lastName": "Horning",
                            "middleNames": [
                                "J."
                            ]
                        }
                    },
                    {
                        "fragments": [],
                        "text": "J. Horning"
                    }
                ]
            ],
            "badges": [],
            "citationContexts": [],
            "corpusId": 60515006,
            "fieldsOfStudy": [
                "Linguistics"
            ],
            "id": "ec350b29e088e3335d4c16dee51ef95cb2eddb93",
            "isKey": false,
            "numCitedBy": 279,
            "numCiting": 0,
            "paperAbstract": {
                "fragments": [],
                "text": ""
            },
            "slug": "A-study-of-grammatical-inference-Horning",
            "title": {
                "fragments": [],
                "text": "A study of grammatical inference"
            },
            "venue": {
                "fragments": [],
                "text": ""
            },
            "year": 1969
        },
        {
            "authors": [
                [
                    {
                        "bitmap$0": false,
                        "ids": [
                            "2109503620"
                        ],
                        "name": "Temple F. Smith",
                        "slug": "Temple-F.-Smith",
                        "structuredName": {
                            "firstName": "Temple",
                            "lastName": "Smith",
                            "middleNames": [
                                "F."
                            ]
                        }
                    },
                    {
                        "fragments": [],
                        "text": "Temple F. Smith"
                    }
                ]
            ],
            "badges": [],
            "citationContexts": [],
            "corpusId": 4276691,
            "fieldsOfStudy": [
                "Biology",
                "Medicine"
            ],
            "id": "0b4d43ef0051a225e07af8194e81007ebba8d787",
            "isKey": false,
            "numCitedBy": 705,
            "numCiting": 0,
            "paperAbstract": {
                "fragments": [],
                "text": ""
            },
            "slug": "Occam's-razor-Smith",
            "title": {
                "fragments": [],
                "text": "Occam's razor"
            },
            "venue": {
                "fragments": [],
                "text": "Nature"
            },
            "year": 1980
        },
        {
            "authors": [],
            "badges": [
                {
                    "id": "OPEN_ACCESS"
                }
            ],
            "citationContexts": [],
            "corpusId": 4148010,
            "fieldsOfStudy": [],
            "id": "993de2892811b5dc507bbb618a7233cbf7a7f6a8",
            "isKey": false,
            "numCitedBy": 1456,
            "numCiting": 0,
            "paperAbstract": {
                "fragments": [],
                "text": ""
            },
            "slug": "Journal-of-the-Association-for-Computing-Machinery",
            "title": {
                "fragments": [],
                "text": "Journal of the Association for Computing Machinery"
            },
            "venue": {
                "fragments": [],
                "text": "Nature"
            },
            "year": 1961
        },
        {
            "authors": [
                [
                    {
                        "bitmap$0": false,
                        "ids": [
                            "2228970"
                        ],
                        "name": "R. V. Freivald",
                        "slug": "R.-V.-Freivald",
                        "structuredName": {
                            "firstName": "R.",
                            "lastName": "Freivald",
                            "middleNames": [
                                "V."
                            ]
                        }
                    },
                    {
                        "fragments": [],
                        "text": "R. V. Freivald"
                    }
                ]
            ],
            "badges": [],
            "citationContexts": [],
            "corpusId": 28081814,
            "fieldsOfStudy": [
                "Mathematics"
            ],
            "id": "c5342c5b9302a496343e974e5a333a6281042827",
            "isKey": false,
            "numCitedBy": 17,
            "numCiting": 3,
            "paperAbstract": {
                "fragments": [],
                "text": ""
            },
            "slug": "Functions-Computable-in-the-Limit-by-Probabilistic-Freivald",
            "title": {
                "fragments": [],
                "text": "Functions Computable in the Limit by Probabilistic Machines"
            },
            "venue": {
                "fragments": [],
                "text": "MFCS"
            },
            "year": 1974
        },
        {
            "authors": [
                [
                    {
                        "bitmap$0": false,
                        "ids": [
                            "48453169"
                        ],
                        "name": "S. Rudich",
                        "slug": "S.-Rudich",
                        "structuredName": {
                            "firstName": "Steven",
                            "lastName": "Rudich",
                            "middleNames": []
                        }
                    },
                    {
                        "fragments": [],
                        "text": "S. Rudich"
                    }
                ]
            ],
            "badges": [],
            "citationContexts": [],
            "corpusId": 52817300,
            "fieldsOfStudy": [
                "Mathematics"
            ],
            "id": "362eeae8a422377c459fec78d985bdcfbe88ab16",
            "isKey": false,
            "numCitedBy": 32,
            "numCiting": 7,
            "paperAbstract": {
                "fragments": [],
                "text": "Outline Consider a Markov .Chain of the following nonstandard kind: it is a totally connected finite state machine with a 0 and 1 transition arrow out of each state and probabilities attached to these transitions. The probabilities on the transitions out of any state must sum to 1. ' Suppose one is given a black box containing such a Finite State Markov Chain. Suppose the box has a start button which, .when pressed, causes the box to start generating Os and Is forever. At each moment in time whatever state the Markov Chain is in, i~ selects a 0 or 1 with the probability indicated on the transition arrows, outputs that 0 or 1, then goes to the indicated state. The question is this: can one determine the finite state Markov Chain from the output of the box? Of course, if one knows the' underlying finite state diagram of the Markov Chain, i.e., the"
            },
            "slug": "Inferring-the-Structure-of-a-Markov-Chain-from-its-Rudich",
            "title": {
                "fragments": [],
                "text": "Inferring the Structure of a Markov Chain from its Output"
            },
            "tldr": {
                "abstractSimilarityScore": 100,
                "text": "Outline Consider a Markov .Chain of the following nonstandard kind: it is a totally connected finite state machine with a 0 and 1 transition arrow out of each state and probabilities attached to these transitions."
            },
            "venue": {
                "fragments": [],
                "text": "FOCS"
            },
            "year": 1985
        },
        {
            "authors": [],
            "badges": [],
            "citationContexts": [],
            "fieldsOfStudy": [],
            "isKey": false,
            "numCitedBy": 0,
            "numCiting": 0,
            "paperAbstract": {
                "fragments": [],
                "text": ""
            },
            "slug": "+",
            "title": {
                "fragments": [],
                "text": "Learning disjunctions of conjunctions"
            },
            "venue": {
                "fragments": [],
                "text": "Proceedings of the 9 th IJCAI"
            },
            "year": 1985
        },
        {
            "authors": [],
            "badges": [],
            "citationContexts": [],
            "fieldsOfStudy": [],
            "isKey": false,
            "numCitedBy": 0,
            "numCiting": 0,
            "paperAbstract": {
                "fragments": [],
                "text": ""
            },
            "slug": "+",
            "title": {
                "fragments": [],
                "text": "Remarks on the difficulty of finding a minimal disjunctive normal form for Boolean functions"
            },
            "venue": {
                "fragments": [],
                "text": "Remarks on the difficulty of finding a minimal disjunctive normal form for Boolean functions"
            }
        },
        {
            "authors": [],
            "badges": [],
            "citationContexts": [],
            "fieldsOfStudy": [],
            "isKey": false,
            "numCitedBy": 0,
            "numCiting": 0,
            "paperAbstract": {
                "fragments": [],
                "text": ""
            },
            "slug": "+",
            "title": {
                "fragments": [],
                "text": "RECEIVED AUGUST REVISED JUNE"
            },
            "venue": {
                "fragments": [],
                "text": "RECEIVED AUGUST REVISED JUNE"
            },
            "year": 1986
        },
        {
            "authors": [],
            "badges": [],
            "citationContexts": [],
            "fieldsOfStudy": [],
            "isKey": false,
            "numCitedBy": 0,
            "numCiting": 0,
            "paperAbstract": {
                "fragments": [],
                "text": ""
            },
            "slug": "+",
            "title": {
                "fragments": [],
                "text": "Worst case behaviour of graph coloring algorithms"
            },
            "venue": {
                "fragments": [],
                "text": "Proceedings of the 5th South-Eastern Conference on Combinatorics, Graph Theory, and Computing. Utilitas Mathematics"
            },
            "year": 1974
        },
        {
            "authors": [],
            "badges": [],
            "citationContexts": [],
            "fieldsOfStudy": [],
            "isKey": false,
            "numCitedBy": 0,
            "numCiting": 0,
            "paperAbstract": {
                "fragments": [],
                "text": ""
            },
            "slug": "+",
            "title": {
                "fragments": [],
                "text": "Machine Learning: An Artljicial ZnteNigence Approach. Tioga"
            },
            "venue": {
                "fragments": [],
                "text": "Machine Learning: An Artljicial ZnteNigence Approach. Tioga"
            },
            "year": 1983
        },
        {
            "authors": [],
            "badges": [],
            "citationContexts": [],
            "fieldsOfStudy": [],
            "isKey": false,
            "numCitedBy": 0,
            "numCiting": 0,
            "paperAbstract": {
                "fragments": [],
                "text": ""
            },
            "slug": "+",
            "title": {
                "fragments": [],
                "text": "Universal sorting problems"
            },
            "venue": {
                "fragments": [],
                "text": "Prob . Pered . Inf"
            },
            "year": 1973
        },
        {
            "authors": [],
            "badges": [],
            "citationContexts": [],
            "fieldsOfStudy": [],
            "isKey": false,
            "numCitedBy": 0,
            "numCiting": 0,
            "paperAbstract": {
                "fragments": [],
                "text": ""
            },
            "slug": "+",
            "title": {
                "fragments": [],
                "text": "Universal sorting problems"
            },
            "venue": {
                "fragments": [],
                "text": "Prob. Pered. Inf"
            },
            "year": 1973
        },
        {
            "authors": [],
            "badges": [],
            "citationContexts": [],
            "fieldsOfStudy": [],
            "isKey": false,
            "numCitedBy": 0,
            "numCiting": 0,
            "paperAbstract": {
                "fragments": [],
                "text": ""
            },
            "slug": "+",
            "title": {
                "fragments": [],
                "text": "Remarks on the difficulty of finding a minimal disjunctive normal form for Boolean functions"
            },
            "venue": {
                "fragments": [],
                "text": ""
            }
        },
        {
            "authors": [],
            "badges": [],
            "citationContexts": [],
            "fieldsOfStudy": [],
            "isKey": false,
            "numCitedBy": 0,
            "numCiting": 0,
            "paperAbstract": {
                "fragments": [],
                "text": ""
            },
            "slug": "+",
            "title": {
                "fragments": [],
                "text": "Probabilistic synthesis of enumerated classes of functions"
            },
            "venue": {
                "fragments": [],
                "text": "Sov. Math. Dokl"
            },
            "year": 1975
        },
        {
            "authors": [],
            "badges": [],
            "citationContexts": [],
            "fieldsOfStudy": [],
            "isKey": false,
            "numCitedBy": 0,
            "numCiting": 0,
            "paperAbstract": {
                "fragments": [],
                "text": ""
            },
            "slug": "+",
            "title": {
                "fragments": [],
                "text": "On machine inductive inference of approximations"
            },
            "venue": {
                "fragments": [],
                "text": ""
            }
        },
        {
            "authors": [],
            "badges": [],
            "citationContexts": [],
            "fieldsOfStudy": [],
            "isKey": false,
            "numCitedBy": 0,
            "numCiting": 0,
            "paperAbstract": {
                "fragments": [],
                "text": ""
            },
            "slug": "+",
            "title": {
                "fragments": [],
                "text": "Worst case behaviour of graph coloring algorithms"
            },
            "venue": {
                "fragments": [],
                "text": "Proceedings of the 5 th South - Eastern Conference on Combinatorics , Graph Theory , and Computing"
            }
        },
        {
            "authors": [],
            "badges": [],
            "citationContexts": [],
            "fieldsOfStudy": [],
            "isKey": false,
            "numCitedBy": 0,
            "numCiting": 0,
            "paperAbstract": {
                "fragments": [],
                "text": ""
            },
            "slug": "+",
            "title": {
                "fragments": [],
                "text": "Finite identification of general recursive functions by probabilistic strategies"
            },
            "venue": {
                "fragments": [],
                "text": "Proceedings of the Conference on Algebraic , Arithmetic , and Categorial Methods in Computation Theory"
            },
            "year": 1979
        },
        {
            "authors": [],
            "badges": [],
            "citationContexts": [],
            "fieldsOfStudy": [],
            "isKey": false,
            "numCitedBy": 0,
            "numCiting": 0,
            "paperAbstract": {
                "fragments": [],
                "text": ""
            },
            "slug": "+",
            "title": {
                "fragments": [],
                "text": "Finite identification of general recursive functions by probabilistic strategies"
            },
            "venue": {
                "fragments": [],
                "text": "Proceedings of the Conference on Algebraic, Arithmetic, and Categorial Methods in Computation Theory"
            },
            "year": 1979
        },
        {
            "authors": [],
            "badges": [],
            "citationContexts": [],
            "fieldsOfStudy": [],
            "isKey": false,
            "numCitedBy": 0,
            "numCiting": 0,
            "paperAbstract": {
                "fragments": [],
                "text": ""
            },
            "slug": "+",
            "title": {
                "fragments": [],
                "text": "Probabilistic synthesis of enumerated classes of functions"
            },
            "venue": {
                "fragments": [],
                "text": "Sov . Math . Dokl ."
            },
            "year": 1975
        }
    ],
    "meta_info": {
        "citationIntent": "all",
        "citationIntentCount": {
            "background": 3,
            "methodology": 1,
            "result": 2
        },
        "citationType": "citedPapers",
        "pageNumber": 1,
        "requestedPageSize": 10,
        "sort": "relevance",
        "totalCitations": 45,
        "totalPages": 5
    },
    "page_url": "https://www.semanticscholar.org/paper/Computational-limitations-on-learning-from-examples-Pitt-Valiant/93849122caf1b10c9611eddb707e0720441c73f6?sort=total-citations"
}